<?xml version="1.0" encoding="utf-8"?>

<outputs>
  <output_group name="FLOW WRB Q_DISCHARG Skill Assessment" monthly="y" >
    <output name="USGS 14166000_flow_WILLAMETTE RIVER AT HARRISBURG, OR_23763337" query="COMID=23763337" value="Q_DISCHARG*35.3146667" type="sum" domain="reach"
      obs="..\Observations\Willamette\USGS 14166000_flow_WILLAMETTE RIVER AT HARRISBURG, OR_23763337.csv" format="E0" />
    <output name="USGS 14171600_flow_WILLAMETTE RIVER AT CORVALLIS, OR_23762877" query="COMID=23762877" value="Q_DISCHARG*35.3146667" type="sum" domain="reach"
      obs="..\Observations\Willamette\USGS 14171600_flow_WILLAMETTE RIVER AT CORVALLIS, OR_23762877.csv" format="E0" />  
    <output name="USGS 14174000_flow_WILLAMETTE RIVER AT ALBANY, OR_23762845" query="COMID=23762845" value="Q_DISCHARG*35.3146667" type="sum" domain="reach"
      obs="..\Observations\Willamette\USGS 14174000_flow_WILLAMETTE RIVER AT ALBANY, OR_23762845.csv" format="E0" />
    <output name="USGS 14191000_flow_WILLAMETTE RIVER AT SALEM, OR_23791093" query="COMID=23791093" value="Q_DISCHARG*35.3146667" type="sum" domain="reach"
      obs="..\Observations\Willamette\USGS 14191000_flow_WILLAMETTE RIVER AT SALEM, OR_23791093.csv" format="E0" />
    <output name="USGS 14197900_flow_WILLAMETTE RIVER AT NEWBERG, OR_23791305" query="COMID=23791305" value="Q_DISCHARG*35.3146667" type="sum" domain="reach"
      obs="..\Observations\Willamette\USGS 14197900_flow_WILLAMETTE RIVER AT NEWBERG, OR_23791305.csv" format="E0" />
    <output name="USGS 14211720_flow_WILLAMETTE RIVER AT PORTLAND, OR_23815040" query="COMID=23815040" value="Q_DISCHARG*35.3146667" type="sum" domain="reach"
      obs="..\Observations\Willamette\USGS 14211720_flow_WILLAMETTE RIVER AT PORTLAND, OR_23815040.csv" format="E0" />
  </output_group>

</outputs>
